{"droneId":31,"msgType":"'HOT'","temp":134.0,"time":"'2019-05-11 21:54:05.104057'","geoPos":{"x":98218,"y":15288,"alt":2469}}
{"droneId":31,"msgType":"'OK'","temp":43.0,"time":"'2019-05-11 21:54:06.743794'","geoPos":{"x":73971,"y":3299,"alt":52}}
{"droneId":31,"msgType":"'OK'","temp":40.0,"time":"'2019-05-11 21:54:07.772738'","geoPos":{"x":28538,"y":89408,"alt":317}}
{"droneId":31,"msgType":"'OK'","temp":20.0,"time":"'2019-05-11 21:54:09.773953'","geoPos":{"x":96186,"y":59981,"alt":2614}}
{"droneId":31,"msgType":"'HOT'","temp":57.0,"time":"'2019-05-11 21:54:11.338384'","geoPos":{"x":66530,"y":33154,"alt":1774}}
{"droneId":31,"msgType":"'HOT'","temp":100.0,"time":"'2019-05-11 21:54:13.1363'","geoPos":{"x":41770,"y":84766,"alt":3088}}
{"droneId":31,"msgType":"'COLD'","temp":8.0,"time":"'2019-05-11 21:54:14.402656'","geoPos":{"x":88903,"y":47409,"alt":3341}}
{"droneId":31,"msgType":"'HOT'","temp":133.0,"time":"'2019-05-11 21:54:16.042842'","geoPos":{"x":28311,"y":74385,"alt":2986}}
{"droneId":31,"msgType":"'OK'","temp":22.0,"time":"'2019-05-11 21:54:17.44906'","geoPos":{"x":74813,"y":4332,"alt":1917}}
{"droneId":31,"msgType":"'HOT'","temp":92.0,"time":"'2019-05-11 21:54:18.964318'","geoPos":{"x":57109,"y":55222,"alt":1225}}
{"droneId":31,"msgType":"'HOT'","temp":120.0,"time":"'2019-05-11 21:54:20.756134'","geoPos":{"x":32955,"y":96435,"alt":3750}}
{"droneId":31,"msgType":"'HOT'","temp":76.0,"time":"'2019-05-11 21:54:22.400614'","geoPos":{"x":37384,"y":67899,"alt":2294}}
{"droneId":31,"msgType":"'OK'","temp":22.0,"time":"'2019-05-11 21:54:23.569735'","geoPos":{"x":23582,"y":83963,"alt":1120}}
{"droneId":31,"msgType":"'HOT'","temp":69.0,"time":"'2019-05-11 21:54:25.242066'","geoPos":{"x":56273,"y":39940,"alt":2237}}
{"droneId":31,"msgType":"'COLD'","temp":6.0,"time":"'2019-05-11 21:54:27.018442'","geoPos":{"x":93711,"y":42066,"alt":2244}}
{"droneId":31,"msgType":"'HOT'","temp":93.0,"time":"'2019-05-11 21:54:28.10297'","geoPos":{"x":99191,"y":96796,"alt":2789}}
{"droneId":31,"msgType":"'HOT'","temp":102.0,"time":"'2019-05-11 21:54:29.776963'","geoPos":{"x":17719,"y":95761,"alt":558}}
{"droneId":31,"msgType":"'HOT'","temp":104.0,"time":"'2019-05-11 21:54:31.330285'","geoPos":{"x":62376,"y":51769,"alt":1712}}
{"droneId":31,"msgType":"'HOT'","temp":111.0,"time":"'2019-05-11 21:54:32.979576'","geoPos":{"x":8609,"y":12535,"alt":443}}
{"droneId":31,"msgType":"'HOT'","temp":88.0,"time":"'2019-05-11 21:54:34.955606'","geoPos":{"x":98489,"y":63410,"alt":1262}}
{"droneId":31,"msgType":"'HOT'","temp":85.0,"time":"'2019-05-11 21:54:36.500864'","geoPos":{"x":9421,"y":4898,"alt":3484}}
{"droneId":31,"msgType":"'OK'","temp":31.0,"time":"'2019-05-11 21:54:38.024239'","geoPos":{"x":26719,"y":78684,"alt":1486}}
{"droneId":31,"msgType":"'HOT'","temp":109.0,"time":"'2019-05-11 21:54:39.81515'","geoPos":{"x":57704,"y":29979,"alt":3494}}
{"droneId":31,"msgType":"'OK'","temp":21.0,"time":"'2019-05-11 21:54:40.851961'","geoPos":{"x":31373,"y":67586,"alt":2763}}
{"droneId":31,"msgType":"'HOT'","temp":56.0,"time":"'2019-05-11 21:54:42.297207'","geoPos":{"x":15342,"y":3907,"alt":523}}
{"droneId":31,"msgType":"'HOT'","temp":55.0,"time":"'2019-05-11 21:54:43.637765'","geoPos":{"x":22211,"y":82326,"alt":2645}}
{"droneId":31,"msgType":"'HOT'","temp":83.0,"time":"'2019-05-11 21:54:44.836005'","geoPos":{"x":5051,"y":23727,"alt":3143}}
{"droneId":31,"msgType":"'OK'","temp":18.0,"time":"'2019-05-11 21:54:46.563244'","geoPos":{"x":1150,"y":34093,"alt":2298}}
{"droneId":31,"msgType":"'OK'","temp":13.0,"time":"'2019-05-11 21:54:47.892688'","geoPos":{"x":93605,"y":36244,"alt":861}}
{"droneId":31,"msgType":"'HOT'","temp":95.0,"time":"'2019-05-11 21:54:49.008745'","geoPos":{"x":23200,"y":87282,"alt":1674}}
{"droneId":31,"msgType":"'HOT'","temp":60.0,"time":"'2019-05-11 21:54:50.075784'","geoPos":{"x":61687,"y":92764,"alt":469}}
{"droneId":31,"msgType":"'OK'","temp":28.0,"time":"'2019-05-11 21:54:51.148895'","geoPos":{"x":12865,"y":90958,"alt":3724}}
{"droneId":31,"msgType":"'HOT'","temp":118.0,"time":"'2019-05-11 21:54:52.273242'","geoPos":{"x":62137,"y":41789,"alt":1063}}
{"droneId":31,"msgType":"'HOT'","temp":93.0,"time":"'2019-05-11 21:54:53.811721'","geoPos":{"x":81022,"y":73202,"alt":3769}}
{"droneId":31,"msgType":"'HOT'","temp":103.0,"time":"'2019-05-11 21:54:55.359917'","geoPos":{"x":11830,"y":18086,"alt":1213}}
{"droneId":31,"msgType":"'HOT'","temp":52.0,"time":"'2019-05-11 21:54:57.116829'","geoPos":{"x":66877,"y":60347,"alt":223}}
{"droneId":31,"msgType":"'OK'","temp":27.0,"time":"'2019-05-11 21:54:59.084976'","geoPos":{"x":60622,"y":97895,"alt":288}}
{"droneId":31,"msgType":"'HOT'","temp":70.0,"time":"'2019-05-11 21:55:01.076918'","geoPos":{"x":55031,"y":83649,"alt":2725}}
{"droneId":31,"msgType":"'HOT'","temp":61.0,"time":"'2019-05-11 21:55:02.403964'","geoPos":{"x":4508,"y":74432,"alt":582}}
{"droneId":31,"msgType":"'HOT'","temp":62.0,"time":"'2019-05-11 21:55:04.25973'","geoPos":{"x":78360,"y":71976,"alt":3286}}
{"droneId":31,"msgType":"'OK'","temp":13.0,"time":"'2019-05-11 21:55:06.216419'","geoPos":{"x":53198,"y":59957,"alt":3094}}
{"droneId":31,"msgType":"'OK'","temp":41.0,"time":"'2019-05-11 21:55:07.321937'","geoPos":{"x":57526,"y":30467,"alt":2065}}
{"droneId":31,"msgType":"'OK'","temp":33.0,"time":"'2019-05-11 21:55:08.784797'","geoPos":{"x":73835,"y":23118,"alt":1010}}
{"droneId":31,"msgType":"'HOT'","temp":91.0,"time":"'2019-05-11 21:55:10.262459'","geoPos":{"x":61760,"y":16614,"alt":21}}
{"droneId":31,"msgType":"'HOT'","temp":59.0,"time":"'2019-05-11 21:55:11.415287'","geoPos":{"x":38434,"y":40319,"alt":2432}}
{"droneId":31,"msgType":"'HOT'","temp":60.0,"time":"'2019-05-11 21:55:12.564539'","geoPos":{"x":94063,"y":54857,"alt":2763}}
{"droneId":31,"msgType":"'OK'","temp":18.0,"time":"'2019-05-11 21:55:14.295273'","geoPos":{"x":97077,"y":90544,"alt":3520}}
{"droneId":31,"msgType":"'HOT'","temp":75.0,"time":"'2019-05-11 21:55:15.834901'","geoPos":{"x":16820,"y":15272,"alt":1308}}
{"droneId":31,"msgType":"'HOT'","temp":117.0,"time":"'2019-05-11 21:55:16.979493'","geoPos":{"x":3130,"y":74859,"alt":2157}}
{"droneId":31,"msgType":"'HOT'","temp":62.0,"time":"'2019-05-11 21:55:18.319049'","geoPos":{"x":53942,"y":50368,"alt":3249}}
{"droneId":31,"msgType":"'HOT'","temp":77.0,"time":"'2019-05-11 21:55:20.102397'","geoPos":{"x":11537,"y":55985,"alt":142}}
{"droneId":31,"msgType":"'HOT'","temp":100.0,"time":"'2019-05-11 21:55:21.320027'","geoPos":{"x":42383,"y":79174,"alt":2238}}
{"droneId":31,"msgType":"'HOT'","temp":123.0,"time":"'2019-05-11 21:55:22.817179'","geoPos":{"x":28396,"y":53224,"alt":1883}}
{"droneId":31,"msgType":"'HOT'","temp":125.0,"time":"'2019-05-11 21:55:24.564866'","geoPos":{"x":66687,"y":33961,"alt":3171}}
{"droneId":31,"msgType":"'OK'","temp":18.0,"time":"'2019-05-11 21:55:26.531821'","geoPos":{"x":73254,"y":40492,"alt":2427}}
{"droneId":31,"msgType":"'HOT'","temp":85.0,"time":"'2019-05-11 21:55:27.947396'","geoPos":{"x":56432,"y":22906,"alt":1310}}
{"droneId":31,"msgType":"'HOT'","temp":118.0,"time":"'2019-05-11 21:55:29.087372'","geoPos":{"x":34552,"y":85063,"alt":99}}
{"droneId":31,"msgType":"'HOT'","temp":101.0,"time":"'2019-05-11 21:55:30.518868'","geoPos":{"x":92401,"y":8866,"alt":3844}}
{"droneId":31,"msgType":"'HOT'","temp":131.0,"time":"'2019-05-11 21:55:31.552222'","geoPos":{"x":80772,"y":4630,"alt":3658}}
{"droneId":31,"msgType":"'OK'","temp":21.0,"time":"'2019-05-11 21:55:33.335483'","geoPos":{"x":4009,"y":85191,"alt":839}}
{"droneId":31,"msgType":"'OK'","temp":28.0,"time":"'2019-05-11 21:55:35.181568'","geoPos":{"x":14249,"y":97527,"alt":2768}}
{"droneId":31,"msgType":"'HOT'","temp":75.0,"time":"'2019-05-11 21:55:36.196298'","geoPos":{"x":43719,"y":27618,"alt":2797}}
{"droneId":31,"msgType":"'HOT'","temp":114.0,"time":"'2019-05-11 21:55:37.286193'","geoPos":{"x":45554,"y":15438,"alt":98}}
{"droneId":31,"msgType":"'HOT'","temp":109.0,"time":"'2019-05-11 21:55:38.563713'","geoPos":{"x":71073,"y":59960,"alt":1511}}
{"droneId":31,"msgType":"'HOT'","temp":109.0,"time":"'2019-05-11 21:55:40.433058'","geoPos":{"x":8694,"y":46333,"alt":1360}}
{"droneId":31,"msgType":"'HOT'","temp":65.0,"time":"'2019-05-11 21:55:41.693255'","geoPos":{"x":30533,"y":31652,"alt":688}}
{"droneId":31,"msgType":"'HOT'","temp":109.0,"time":"'2019-05-11 21:55:43.619286'","geoPos":{"x":17377,"y":75742,"alt":3250}}
{"droneId":31,"msgType":"'HOT'","temp":125.0,"time":"'2019-05-11 21:55:45.599722'","geoPos":{"x":52231,"y":69318,"alt":3846}}
{"droneId":31,"msgType":"'HOT'","temp":119.0,"time":"'2019-05-11 21:55:47.385943'","geoPos":{"x":14857,"y":74638,"alt":2083}}
{"droneId":31,"msgType":"'COLD'","temp":6.0,"time":"'2019-05-11 21:55:49.200043'","geoPos":{"x":15955,"y":98330,"alt":1190}}
{"droneId":31,"msgType":"'HOT'","temp":113.0,"time":"'2019-05-11 21:55:51.006929'","geoPos":{"x":47359,"y":19660,"alt":1106}}
{"droneId":31,"msgType":"'HOT'","temp":119.0,"time":"'2019-05-11 21:55:52.202212'","geoPos":{"x":93557,"y":17139,"alt":3688}}
{"droneId":31,"msgType":"'HOT'","temp":122.0,"time":"'2019-05-11 21:55:54.152684'","geoPos":{"x":98551,"y":77259,"alt":849}}
{"droneId":31,"msgType":"'OK'","temp":10.0,"time":"'2019-05-11 21:55:55.887045'","geoPos":{"x":20312,"y":26435,"alt":3797}}
{"droneId":31,"msgType":"'HOT'","temp":92.0,"time":"'2019-05-11 21:55:57.153236'","geoPos":{"x":59847,"y":49025,"alt":1316}}
{"droneId":31,"msgType":"'OK'","temp":39.0,"time":"'2019-05-11 21:55:58.918731'","geoPos":{"x":8829,"y":52307,"alt":540}}
{"droneId":31,"msgType":"'HOT'","temp":59.0,"time":"'2019-05-11 21:56:00.1901'","geoPos":{"x":95405,"y":2391,"alt":2103}}
{"droneId":31,"msgType":"'OK'","temp":21.0,"time":"'2019-05-11 21:56:01.224369'","geoPos":{"x":59477,"y":9719,"alt":2945}}
{"droneId":31,"msgType":"'HOT'","temp":53.0,"time":"'2019-05-11 21:56:02.716847'","geoPos":{"x":694,"y":54612,"alt":2488}}
{"droneId":31,"msgType":"'OK'","temp":38.0,"time":"'2019-05-11 21:56:04.702593'","geoPos":{"x":8309,"y":12811,"alt":3743}}
{"droneId":31,"msgType":"'HOT'","temp":94.0,"time":"'2019-05-11 21:56:06.458807'","geoPos":{"x":49324,"y":83415,"alt":3553}}
{"droneId":31,"msgType":"'HOT'","temp":90.0,"time":"'2019-05-11 21:56:08.437791'","geoPos":{"x":252,"y":13662,"alt":3981}}
{"droneId":31,"msgType":"'OK'","temp":49.0,"time":"'2019-05-11 21:56:09.503953'","geoPos":{"x":52312,"y":94483,"alt":3471}}
{"droneId":31,"msgType":"'HOT'","temp":56.0,"time":"'2019-05-11 21:56:11.457956'","geoPos":{"x":74298,"y":42256,"alt":1362}}
{"droneId":31,"msgType":"'OK'","temp":40.0,"time":"'2019-05-11 21:56:13.448125'","geoPos":{"x":85066,"y":91173,"alt":243}}
{"droneId":31,"msgType":"'HOT'","temp":83.0,"time":"'2019-05-11 21:56:14.764112'","geoPos":{"x":44780,"y":26527,"alt":1677}}
{"droneId":31,"msgType":"'HOT'","temp":113.0,"time":"'2019-05-11 21:56:16.715071'","geoPos":{"x":22208,"y":61839,"alt":215}}
{"droneId":31,"msgType":"'HOT'","temp":55.0,"time":"'2019-05-11 21:56:17.933305'","geoPos":{"x":86755,"y":53009,"alt":2388}}
{"droneId":31,"msgType":"'HOT'","temp":82.0,"time":"'2019-05-11 21:56:18.990401'","geoPos":{"x":2489,"y":90418,"alt":3360}}
{"droneId":31,"msgType":"'HOT'","temp":105.0,"time":"'2019-05-11 21:56:20.814968'","geoPos":{"x":21259,"y":90614,"alt":3435}}
{"droneId":31,"msgType":"'HOT'","temp":79.0,"time":"'2019-05-11 21:56:22.437263'","geoPos":{"x":64181,"y":42210,"alt":212}}
{"droneId":31,"msgType":"'OK'","temp":16.0,"time":"'2019-05-11 21:56:23.799659'","geoPos":{"x":18181,"y":55312,"alt":2397}}
{"droneId":31,"msgType":"'HOT'","temp":64.0,"time":"'2019-05-11 21:56:25.441083'","geoPos":{"x":40484,"y":45176,"alt":3101}}
{"droneId":31,"msgType":"'HOT'","temp":126.0,"time":"'2019-05-11 21:56:26.924084'","geoPos":{"x":28577,"y":12254,"alt":2547}}
{"droneId":31,"msgType":"'OK'","temp":23.0,"time":"'2019-05-11 21:56:28.22657'","geoPos":{"x":73129,"y":72192,"alt":3711}}
{"droneId":31,"msgType":"'HOT'","temp":125.0,"time":"'2019-05-11 21:56:29.743782'","geoPos":{"x":50334,"y":16747,"alt":1399}}
{"droneId":31,"msgType":"'OK'","temp":46.0,"time":"'2019-05-11 21:56:31.142936'","geoPos":{"x":59830,"y":98745,"alt":368}}
{"droneId":31,"msgType":"'HOT'","temp":63.0,"time":"'2019-05-11 21:56:32.717522'","geoPos":{"x":51917,"y":12014,"alt":3325}}
{"droneId":31,"msgType":"'HOT'","temp":96.0,"time":"'2019-05-11 21:56:33.790749'","geoPos":{"x":97253,"y":54487,"alt":3111}}
{"droneId":31,"msgType":"'HOT'","temp":69.0,"time":"'2019-05-11 21:56:35.154652'","geoPos":{"x":3616,"y":92057,"alt":3323}}
