{"droneId":10,"msgType":"'OK'","temp":88.0,"time":"'2019-05-11 23:14:46.828849'","geoPos":{"x":83351,"y":72631,"alt":1320}}
{"droneId":10,"msgType":"'OK'","temp":83.0,"time":"'2019-05-11 23:15:08.297809'","geoPos":{"x":47686,"y":40627,"alt":2499}}
{"droneId":10,"msgType":"'OK'","temp":13.0,"time":"'2019-05-11 23:15:31.413809'","geoPos":{"x":87260,"y":60817,"alt":1812}}
{"droneId":10,"msgType":"'ERROR'","temp":99.0,"time":"'2019-05-11 23:15:52.125707'","geoPos":{"x":89141,"y":46980,"alt":2160}}
{"droneId":10,"msgType":"'OK'","temp":27.0,"time":"'2019-05-11 23:16:13.664843'","geoPos":{"x":28906,"y":95560,"alt":768}}
{"droneId":10,"msgType":"'HOT'","temp":91.0,"time":"'2019-05-11 23:16:34.137341'","geoPos":{"x":47959,"y":31504,"alt":2016}}
{"droneId":10,"msgType":"'HOT'","temp":96.0,"time":"'2019-05-11 23:16:53.248555'","geoPos":{"x":18646,"y":96180,"alt":628}}
{"droneId":10,"msgType":"'COLD'","temp":-12.0,"time":"'2019-05-11 23:17:11.193589'","geoPos":{"x":87461,"y":88122,"alt":2481}}
{"droneId":10,"msgType":"'HOT'","temp":112.0,"time":"'2019-05-11 23:17:33.196688'","geoPos":{"x":32754,"y":35043,"alt":2715}}
{"droneId":10,"msgType":"'COLD'","temp":-15.0,"time":"'2019-05-11 23:17:54.621457'","geoPos":{"x":77123,"y":67656,"alt":3225}}
{"droneId":10,"msgType":"'COLD'","temp":-12.0,"time":"'2019-05-11 23:18:20.145501'","geoPos":{"x":21247,"y":17886,"alt":1482}}
{"droneId":10,"msgType":"'COLD'","temp":7.0,"time":"'2019-05-11 23:18:43.21211'","geoPos":{"x":5634,"y":30047,"alt":2563}}
{"droneId":10,"msgType":"'HOT'","temp":99.0,"time":"'2019-05-11 23:19:07.598532'","geoPos":{"x":81210,"y":97203,"alt":1906}}
{"droneId":10,"msgType":"'COLD'","temp":-13.0,"time":"'2019-05-11 23:19:30.91916'","geoPos":{"x":19287,"y":42830,"alt":2267}}
{"droneId":10,"msgType":"'OK'","temp":42.0,"time":"'2019-05-11 23:19:53.190948'","geoPos":{"x":67782,"y":27457,"alt":422}}
{"droneId":10,"msgType":"'OK'","temp":21.0,"time":"'2019-05-11 23:20:14.575615'","geoPos":{"x":44188,"y":96521,"alt":2450}}
{"droneId":10,"msgType":"'OK'","temp":15.0,"time":"'2019-05-11 23:20:34.060893'","geoPos":{"x":90666,"y":13432,"alt":3614}}
{"droneId":10,"msgType":"'COLD'","temp":-11.0,"time":"'2019-05-11 23:20:57.788498'","geoPos":{"x":16948,"y":12100,"alt":486}}
{"droneId":10,"msgType":"'OK'","temp":70.0,"time":"'2019-05-11 23:21:13.760682'","geoPos":{"x":74916,"y":60832,"alt":2299}}
{"droneId":10,"msgType":"'HOT'","temp":130.0,"time":"'2019-05-11 23:21:41.734421'","geoPos":{"x":28542,"y":90576,"alt":2975}}
{"droneId":10,"msgType":"'OK'","temp":33.0,"time":"'2019-05-11 23:22:07.722221'","geoPos":{"x":83115,"y":54442,"alt":491}}
{"droneId":10,"msgType":"'HOT'","temp":91.0,"time":"'2019-05-11 23:22:31.805614'","geoPos":{"x":12100,"y":52449,"alt":1309}}
{"droneId":10,"msgType":"'OK'","temp":61.0,"time":"'2019-05-11 23:22:54.548279'","geoPos":{"x":99957,"y":33426,"alt":3786}}
{"droneId":10,"msgType":"'HOT'","temp":111.0,"time":"'2019-05-11 23:23:17.066385'","geoPos":{"x":71741,"y":95808,"alt":1057}}
{"droneId":10,"msgType":"'OK'","temp":89.0,"time":"'2019-05-11 23:23:39.968474'","geoPos":{"x":47759,"y":18833,"alt":3244}}
{"droneId":10,"msgType":"'HOT'","temp":103.0,"time":"'2019-05-11 23:24:01.305868'","geoPos":{"x":82109,"y":71100,"alt":435}}
{"droneId":10,"msgType":"'OK'","temp":27.0,"time":"'2019-05-11 23:24:26.974528'","geoPos":{"x":62220,"y":53273,"alt":579}}
{"droneId":10,"msgType":"'ERROR'","temp":75.0,"time":"'2019-05-11 23:24:45.809536'","geoPos":{"x":22049,"y":42768,"alt":130}}
{"droneId":10,"msgType":"'OK'","temp":42.0,"time":"'2019-05-11 23:25:05.088962'","geoPos":{"x":34392,"y":79662,"alt":1494}}
{"droneId":10,"msgType":"'HOT'","temp":109.0,"time":"'2019-05-11 23:25:31.463852'","geoPos":{"x":53824,"y":9100,"alt":1049}}
{"droneId":10,"msgType":"'OK'","temp":88.0,"time":"'2019-05-11 23:25:55.405087'","geoPos":{"x":62953,"y":51369,"alt":1324}}
{"droneId":10,"msgType":"'OK'","temp":71.0,"time":"'2019-05-11 23:26:19.204803'","geoPos":{"x":33304,"y":47705,"alt":734}}
{"droneId":10,"msgType":"'OK'","temp":56.0,"time":"'2019-05-11 23:26:45.383265'","geoPos":{"x":97436,"y":90795,"alt":2324}}
{"droneId":10,"msgType":"'OK'","temp":75.0,"time":"'2019-05-11 23:27:12.814149'","geoPos":{"x":51219,"y":65075,"alt":1643}}
{"droneId":10,"msgType":"'COLD'","temp":3.0,"time":"'2019-05-11 23:27:39.716376'","geoPos":{"x":91153,"y":77212,"alt":200}}
{"droneId":10,"msgType":"'OK'","temp":11.0,"time":"'2019-05-11 23:28:02.174701'","geoPos":{"x":7170,"y":10190,"alt":831}}
{"droneId":10,"msgType":"'OK'","temp":61.0,"time":"'2019-05-11 23:28:26.149964'","geoPos":{"x":16971,"y":17576,"alt":3676}}
{"droneId":10,"msgType":"'OK'","temp":85.0,"time":"'2019-05-11 23:28:48.016237'","geoPos":{"x":26051,"y":52190,"alt":609}}
{"droneId":10,"msgType":"'OK'","temp":87.0,"time":"'2019-05-11 23:29:07.148381'","geoPos":{"x":31970,"y":36250,"alt":2430}}
{"droneId":10,"msgType":"'OK'","temp":14.0,"time":"'2019-05-11 23:29:30.354397'","geoPos":{"x":59870,"y":64364,"alt":60}}
